cribl_utilities/__init__.py
cribl_utilities/ingest.py
cribl_utilities/main.py
cribl_utilities/rest_utilities.py
cribl_utilities/schemas.py
cribl_utilities-2.0.6.dist-info/METADATA
cribl_utilities-2.0.6.dist-info/WHEEL
cribl_utilities-2.0.6.dist-info/entry_points.txt
cribl_utilities-2.0.6.dist-info/RECORD
