Metadata-Version: 2.1
Name: cribl-utilities
Version: 2.0.6
Summary: A comprehensive tool to streamline migrations and validate configurations.
Author: CINQ ICT
Author-email: info@cinqict.nl
Requires-Python: >=3.13,<4.0
Classifier: Programming Language :: Python :: 3
Classifier: Programming Language :: Python :: 3.13
Requires-Dist: PyYAML (>=6.0.2,<7.0.0)
Requires-Dist: click (==8.1.0)
Requires-Dist: pydantic (>=2.10.6,<3.0.0)
Requires-Dist: requests (>=2.32.3,<3.0.0)
Requires-Dist: tomli (>=2.2.1,<3.0.0)
Requires-Dist: typer (>=0.15.1,<0.16.0)
Requires-Dist: yamllint (>=1.35.1,<2.0.0)
